MANIFEST.in
README.rst
setup.py
swissdict/__init__.py
swissdict/main.py
swissdict.egg-info/PKG-INFO
swissdict.egg-info/SOURCES.txt
swissdict.egg-info/dependency_links.txt
swissdict.egg-info/top_level.txt