Metadata-Version: 1.1
Name: swissdict
Version: 0.0.1
Summary: implementation of a multifunctional dict
Home-page: https://github.com/war1or/swissdict
Author: Vasiliy Sinyurin
Author-email: vasiliy@sinyur.in
License: MIT License
Download-URL: https://github.com/war1or/swissdict/tarball/master
Keywords: dict
Platform: UNKNOWN
Classifier: Environment :: Console
Classifier: Intended Audience :: Developers
Classifier: Development Status :: 4 - Beta
Classifier: Programming Language :: Python
Classifier: Programming Language :: Python
Classifier: Programming Language :: Python :: 2
Classifier: Programming Language :: Python :: 2.7
Classifier: Programming Language :: Python :: 3
Classifier: Programming Language :: Python :: 3.4
Classifier: Programming Language :: Python :: 3.5
Requires: python (>= 2.7)
